eth_blocky/__init__.py
eth_blocky/eth_blocky.py
eth_blocky-0.2.3.dist-info/LICENSE
eth_blocky-0.2.3.dist-info/METADATA
eth_blocky-0.2.3.dist-info/WHEEL
eth_blocky-0.2.3.dist-info/RECORD
