Metadata-Version: 2.1
Name: eth-blocky
Version: 0.2.3
Summary: 
Author: vonum
Author-email: vonum.mk@gmail.com
Requires-Python: >=3.11,<4.0
Classifier: Programming Language :: Python :: 3
Classifier: Programming Language :: Python :: 3.11
Requires-Dist: arrow (>=1.2.3,<2.0.0)
Requires-Dist: python-dotenv (>=1.0.0,<2.0.0)
Requires-Dist: web3 (>=6.4.0,<7.0.0)
